ai_intake_bot/__init__.py
ai_intake_bot/core/__init__.py
ai_intake_bot/core/actions.py
ai_intake_bot/core/engine.py
ai_intake_bot/core/llm.py
ai_intake_bot/core/llm_gemini_openai.py
ai_intake_bot/core/llm_registry.py
ai_intake_bot/core/personas.py
ai_intake_bot/core/prompts.py
ai_intake_bot/core/router.py
ai_intake_bot/core/scoring.py
ai_intake_bot/core/session.py
ai_intake_bot/core/templates.py
ai_intake_bot/core/voice.py
ai_intake_bot/rag/embeddings.py
ai_intake_bot/rag/loader.py
ai_intake_bot/rag/retriever.py
ai_intake_bot/rag/splitter.py
ai_intake_bot/rag/vectorstore.py
ai_intake_bot/security/credentials.py
ai_intake_bot-0.1.5.dist-info/licenses/LICENSE
ai_intake_bot-0.1.5.dist-info/METADATA
ai_intake_bot-0.1.5.dist-info/WHEEL
ai_intake_bot-0.1.5.dist-info/entry_points.txt
ai_intake_bot-0.1.5.dist-info/top_level.txt
ai_intake_bot-0.1.5.dist-info/RECORD
