Metadata-Version: 2.4
Name: ai_intake_bot
Version: 0.1.5
Summary: Persona-(session) and RAG-based intake SDK (prototype)
License-Expression: MIT
Requires-Python: >=3.9
License-File: LICENSE
Requires-Dist: pydantic<2,>=1.10
Provides-Extra: dev
Requires-Dist: pytest>=7.0; extra == "dev"
Dynamic: license-file
